django_ajax_tables/__init__.py
django_ajax_tables/templates/django_ajax_tables/ajax_wrapper.html
django_ajax_tables/templatetags/__init__.py
django_ajax_tables/templatetags/ajax_table.py
django_ajax_tables-1.1.1.dist-info/LICENSE
django_ajax_tables-1.1.1.dist-info/METADATA
django_ajax_tables-1.1.1.dist-info/WHEEL
django_ajax_tables-1.1.1.dist-info/top_level.txt
django_ajax_tables-1.1.1.dist-info/RECORD
