Metadata-Version: 2.1
Name: django_ajax_tables
Version: 1.1.1
Summary: Django tag for ajax-enabled tables
Home-page: https://github.com/KiwiTrinsic/django-ajax-tables
Author: Dustin Cotton
Author-email: dcotton@stormpurple.net
License: UNKNOWN
Platform: UNKNOWN
Classifier: Programming Language :: Python :: 3
Classifier: Framework :: Django :: 2.0
Classifier: Framework :: Django :: 2.1
Classifier: Framework :: Django :: 2.2
Classifier: Environment :: Web Environment
Classifier: License :: OSI Approved :: MIT License
Classifier: Intended Audience :: Developers
Classifier: Operating System :: OS Independent
